{
  "Main": {
    "uid": {
      "type": "UID",
      "config": {
        "label": "UID"
      }
    },
    "title": {
      "type": "StructuredText",
      "config": {
        "single": "heading1, heading2, heading3, heading4, heading5, heading6",
        "label": "Title"
      }
    },
    "featured_image": {
      "type": "Image",
      "config": {
        "constraint": {
          "width": 600
        },
        "thumbnails": [],
        "label": "Featured Image"
      }
    },
    "description": {
      "type": "StructuredText",
      "config": {
        "multi": "paragraph, preformatted, heading1, heading2, heading3, heading4, heading5, heading6, strong, em, hyperlink, embed, list-item, o-list-item, rtl",
        "label": "Description",
        "placeholder": "Name  / Year / Material"
      }
    },
    "topofthepops": {
      "type": "Boolean",
      "config": {
        "default_value": false,
        "label": "topOfThePops"
      }
    },
    "images": {
      "type": "Group",
      "config": {
        "fields": {
          "image": {
            "type": "Image",
            "config": {
              "constraint": {
                "width": 1200
              },
              "thumbnails": [],
              "label": "Image"
            }
          },
          "text": {
            "type": "StructuredText",
            "config": {
              "multi": "paragraph, preformatted, heading1, heading2, heading3, heading4, heading5, heading6, strong, em, hyperlink, embed, list-item, o-list-item, rtl",
              "label": "Text",
              "placeholder": "Will appear in bottom right corner"
            }
          }
        },
        "label": "Images"
      }
    }
  }
}
